pybuilder_archetype_api/__init__.py
pybuilder_archetype_api/errors.py
pybuilder_archetype_api/helpers.py
pybuilder_archetype_api/messages.py
pybuilder_archetype_api/resources/__init__.py
pybuilder_archetype_api/resources/gunicorn_config.py
pybuilder_archetype_api/resources/main.py
pybuilder_archetype_api/resources/requirements.txt
pybuilder_archetype_api/resources/wsgi.py
pybuilder_archetype_api/resources/api/api_example.py
pybuilder_archetype_api/resources/config/constants.py
pybuilder_archetype_api-0.1.1.dist-info/METADATA
pybuilder_archetype_api-0.1.1.dist-info/WHEEL
pybuilder_archetype_api-0.1.1.dist-info/namespace_packages.txt
pybuilder_archetype_api-0.1.1.dist-info/top_level.txt
pybuilder_archetype_api-0.1.1.dist-info/zip-safe
pybuilder_archetype_api-0.1.1.dist-info/RECORD
