Metadata-Version: 2.1
Name: pybuilder-archetype-api
Version: 0.1.1
Summary: External plugin for PyBuilder to generate a web service project structure
Home-page: https://github.com/yeuk0/pybuilder-archetype-api
Author: Arturo GL, Diego BM
Author-email: r2d2006@hotmail.com, diegobm92@gmail.com
Maintainer: 
Maintainer-email: 
License: Apache License, Version 2.0
Platform: UNKNOWN
Classifier: Development Status :: 3 - Alpha
Classifier: Programming Language :: Python
